iversions/__init__.py
iversions/iversions.py
iversions-0.0.10.dist-info/LICENSE
iversions-0.0.10.dist-info/WHEEL
iversions-0.0.10.dist-info/METADATA
iversions-0.0.10.dist-info/RECORD
