Metadata-Version: 1.2
Name: iversions
Version: 0.0.10
Summary: A cell magic command for IPython/Jupyter to display name and version of the imported modules
Home-page: https://github.com/iamaziz/iversions
License: UNKNOWN
Author: Aziz Alto
Author-email: iamaziz.alto@gmail.com
Classifier: License :: OSI Approved :: MIT License
